mowgli/__init__.py
mowgli/models.py
mowgli/pl.py
mowgli/score.py
mowgli/tl.py
mowgli/utils.py
mowgli-0.4.0.dist-info/LICENSE
mowgli-0.4.0.dist-info/METADATA
mowgli-0.4.0.dist-info/WHEEL
mowgli-0.4.0.dist-info/RECORD
