Metadata-Version: 2.1
Name: mowgli
Version: 0.4.0
Summary: Mowgli is a novel method for the integration of paired multi-omics data with any type and number of omics, combining integrative Nonnegative Matrix Factorization and Optimal Transport.
License: GPL-3.0-only
Author: Geert-Jan Huizing
Author-email: huizing@ens.fr
Requires-Python: >=3.8,<3.12
Classifier: License :: OSI Approved :: GNU General Public License v3 (GPLv3)
Classifier: Programming Language :: Python :: 3
Classifier: Programming Language :: Python :: 3.8
Classifier: Programming Language :: Python :: 3.9
Classifier: Programming Language :: Python :: 3.10
Classifier: Programming Language :: Python :: 3.11
Provides-Extra: dev
Provides-Extra: docs
Provides-Extra: full
Requires-Dist: anndata (>=0.8.0,<0.9.0)
Requires-Dist: furo (>=2022.12.7,<2023.0.0) ; extra == "docs"
Requires-Dist: gprofiler-official (>=1.0.0,<2.0.0) ; extra == "full"
Requires-Dist: leidenalg (>=0.9.1,<0.10.0) ; extra == "full"
Requires-Dist: matplotlib (>=3.0.0,<4.0.0)
Requires-Dist: mudata (>=0.2.1,<0.3.0)
Requires-Dist: nbsphinx (>=0.8.12,<0.9.0) ; extra == "docs"
Requires-Dist: numpy (>=1.0.0,<2.0.0)
Requires-Dist: pre-commit (>=3.1.1,<4.0.0) ; extra == "dev"
Requires-Dist: scanpy (>=1.0.0,<2.0.0)
Requires-Dist: scikit-learn (>=1.0.0,<2.0.0)
Requires-Dist: scipy (>=1.0.0,<2.0.0)
Requires-Dist: torch (>=1.0.0,<2.0.0)
Requires-Dist: tqdm (>=4.0.0,<5.0.0)
